skpartial/__init__.py
skpartial/pipeline.py
tests/__init__.py
tests/test_docs.py
scikit_partial-0.1.0.dist-info/LICENSE
scikit_partial-0.1.0.dist-info/METADATA
scikit_partial-0.1.0.dist-info/WHEEL
scikit_partial-0.1.0.dist-info/top_level.txt
scikit_partial-0.1.0.dist-info/RECORD
